pyaranet4/__init__.py
pyaranet4/__main__.py
pyaranet4/exceptions.py
pyaranet4/pyaranet4.py
pyaranet4/util.py
pyaranet4-1.0.3.dist-info/LICENSE
pyaranet4-1.0.3.dist-info/METADATA
pyaranet4-1.0.3.dist-info/WHEEL
pyaranet4-1.0.3.dist-info/entry_points.txt
pyaranet4-1.0.3.dist-info/top_level.txt
pyaranet4-1.0.3.dist-info/RECORD
