Metadata-Version: 2.1
Name: pyaranet4
Version: 1.0.3
Summary: A cross-platform Python interface for the Aranet4 CO₂ meter
License: MIT License
Classifier: License :: OSI Approved :: MIT License
Classifier: Natural Language :: English
Requires-Python: >=3.6
License-File: LICENSE
Requires-Dist: bleak (==0.19.0)
Requires-Dist: requests (==2.28.1)
